ccus/__init__.py
ccus/test.py
ccus-1.dist-info/METADATA
ccus-1.dist-info/WHEEL
ccus-1.dist-info/top_level.txt
ccus-1.dist-info/RECORD
