Metadata-Version: 2.4
Name: ccus
Version: 1
Summary: 5
Home-page: 
Author: cw
Author-email: yaogansha@gmial.com
Dynamic: author
Dynamic: author-email
Dynamic: summary
